sos4py/__init__.py
sos4py/main.py
sos4py/sos_2_0_0.py
sos4py/util.py
sos4py-0.3.0.dist-info/AUTHORS.rst
sos4py-0.3.0.dist-info/LICENSE
sos4py-0.3.0.dist-info/METADATA
sos4py-0.3.0.dist-info/WHEEL
sos4py-0.3.0.dist-info/top_level.txt
sos4py-0.3.0.dist-info/RECORD
