Metadata-Version: 2.1
Name: sos4py
Version: 0.3.0
Summary: sos4py is a convenience layer for Python environment to access services from SOS instances.
Home-page: https://github.com/52North/sos4py
Author: Alfredo Chavarria Vargas
Author-email: alchav06@gmail.com
License: Apache Software License 2.0
Download-URL: https://github.com/52North/sos4py/archive/v0.3.0.tar.gz
Keywords: sos4py
Platform: UNKNOWN
Classifier: Development Status :: 2 - Pre-Alpha
Classifier: Intended Audience :: Developers
Classifier: License :: OSI Approved :: Apache Software License
Classifier: Natural Language :: English
Classifier: Programming Language :: Python :: 3
Classifier: Programming Language :: Python :: 3.5
Classifier: Programming Language :: Python :: 3.6
Classifier: Programming Language :: Python :: 3.7
Classifier: Programming Language :: Python :: 3.8
Requires-Python: >=3.5
Requires-Dist: OWSLib
Requires-Dist: pandas
Requires-Dist: geopandas
Requires-Dist: shapely
Requires-Dist: pyproj
